collective.vocabularies.technology-1.0.3-py2.7-nspkg.pth
collective/vocabularies/technology/__init__.py
collective/vocabularies/technology/configure.zcml
collective/vocabularies/technology/interfaces.py
collective/vocabularies/technology/setuphandlers.py
collective/vocabularies/technology/testing.py
collective/vocabularies/technology/vocab.py
collective/vocabularies/technology/browser/__init__.py
collective/vocabularies/technology/browser/configure.zcml
collective/vocabularies/technology/browser/overrides/.gitkeep
collective/vocabularies/technology/browser/static/.gitkeep
collective/vocabularies/technology/databases/.gitkeep
collective/vocabularies/technology/databases/programming_languages.json
collective/vocabularies/technology/locales/collective.vocabularies.technology.pot
collective/vocabularies/technology/locales/update.sh
collective/vocabularies/technology/profiles/default/browserlayer.xml
collective/vocabularies/technology/profiles/default/metadata.xml
collective/vocabularies/technology/profiles/uninstall/browserlayer.xml
collective/vocabularies/technology/tests/__init__.py
collective/vocabularies/technology/tests/test_robot.py
collective/vocabularies/technology/tests/test_setup.py
collective/vocabularies/technology/tests/robot/test_example.robot
collective.vocabularies.technology-1.0.3.dist-info/METADATA
collective.vocabularies.technology-1.0.3.dist-info/RECORD
collective.vocabularies.technology-1.0.3.dist-info/WHEEL
collective.vocabularies.technology-1.0.3.dist-info/entry_points.txt
collective.vocabularies.technology-1.0.3.dist-info/namespace_packages.txt
collective.vocabularies.technology-1.0.3.dist-info/top_level.txt
